Metadata-Version: 1.0
Name: feedo
Version: 1.1.0
Summary: Read, format and output an RSS stream.
Home-page: https://github.com/kamikat/feedo
Author: Kamikat
Author-email: kamikat@banana.moe
License: MIT
Platform: UNKNOWN
